llmsanitize/__init__.py
llmsanitize/base_contamination_checker.py
llmsanitize/closed_data_contamination_checker.py
llmsanitize/open_data_contamination_checker.py
llmsanitize/closed_data_methods/__init__.py
llmsanitize/closed_data_methods/cdd.py
llmsanitize/closed_data_methods/guided_prompting.py
llmsanitize/closed_data_methods/llm.py
llmsanitize/closed_data_methods/min_prob.py
llmsanitize/closed_data_methods/sharded_likelihood.py
llmsanitize/closed_data_methods/ts_guessing_question_based.py
llmsanitize/closed_data_methods/ts_guessing_question_multichoice.py
llmsanitize/configs/__init__.py
llmsanitize/configs/config.py
llmsanitize/configs/main_config.yaml
llmsanitize/open_data_methods/__init__.py
llmsanitize/open_data_methods/exact.py
llmsanitize/open_data_methods/gpt2.py
llmsanitize/open_data_methods/gpt3.py
llmsanitize/open_data_methods/gpt4.py
llmsanitize/open_data_methods/palm.py
llmsanitize/open_data_methods/platypus.py
llmsanitize/prompts/__init__.py
llmsanitize/prompts/guided_prompting/__init__.py
llmsanitize/prompts/guided_prompting/general_instructions.py
llmsanitize/prompts/guided_prompting/guided_instructions.py
llmsanitize/utils/__init__.py
llmsanitize/utils/dataset_utils.py
llmsanitize/utils/embeddings_utils.py
llmsanitize/utils/logger.py
llmsanitize/utils/openai_utils.py
llmsanitize/utils/post_utils.py
llmsanitize/utils/string_utils.py
llmsanitize/utils/string_utils_streaming.py
llmsanitize/utils/utils.py
llmsanitize-0.0.8.dist-info/LICENSE.txt
llmsanitize-0.0.8.dist-info/METADATA
llmsanitize-0.0.8.dist-info/WHEEL
llmsanitize-0.0.8.dist-info/top_level.txt
llmsanitize-0.0.8.dist-info/RECORD
