Metadata-Version: 2.1
Name: llmsanitize
Version: 0.0.8
Summary: LLMSanitize: a package to detect contamination in LLMs
Home-page: https://github.com/ntunlp/LLMSanitize
Author: Mathieu Ravaut (NTU-NLP lab)
License: Apache 2.0
Requires-Python: >=3.9
License-File: LICENSE.txt
Requires-Dist: datasets==2.17.1
Requires-Dist: evaluate==0.4.1
Requires-Dist: huggingface-hub==0.20.3
Requires-Dist: matplotlib==3.8.3
Requires-Dist: nltk==3.8.1
Requires-Dist: numpy==1.26.4
Requires-Dist: openai==1.35.7
Requires-Dist: pandas==2.2.1
Requires-Dist: rouge-score==0.1.2
Requires-Dist: scipy==1.12.0
Requires-Dist: sentence-transformers==3.0.1
Requires-Dist: sentencepiece==0.2.0
Requires-Dist: torch==2.1.2
Requires-Dist: transformers==4.38.0
Requires-Dist: triton==2.1.0
Requires-Dist: vllm==0.3.3
